{"version":{"pluginId":"default","version":"current","label":"Next","banner":null,"badge":false,"noIndex":false,"className":"docs-version-current","isLast":true,"docsSidebars":{"tutorialSidebar":[{"type":"link","label":"簡介","href":"/docs/intro","docId":"intro","unlisted":false},{"type":"link","label":"貢獻者指南","href":"/docs/contribute","docId":"contribute","unlisted":false},{"type":"category","label":"性別焦慮（GD）","collapsible":true,"collapsed":true,"items":[{"type":"link","label":"什麼是性別焦慮（GD）？","href":"/docs/性別焦慮（GD）/gd","docId":"性別焦慮（GD）/gd","unlisted":false},{"type":"link","label":"跨性別女性的性別焦慮","href":"/docs/性別焦慮（GD）/transwomen","docId":"性別焦慮（GD）/transwomen","unlisted":false}]}],"myAutogeneratedSidebar":[{"type":"link","label":"簡介","href":"/docs/intro","docId":"intro","unlisted":false},{"type":"link","label":"貢獻者指南","href":"/docs/contribute","docId":"contribute","unlisted":false},{"type":"category","label":"性別焦慮（GD）","collapsible":true,"collapsed":true,"items":[{"type":"link","label":"什麼是性別焦慮（GD）？","href":"/docs/性別焦慮（GD）/gd","docId":"性別焦慮（GD）/gd","unlisted":false},{"type":"link","label":"跨性別女性的性別焦慮","href":"/docs/性別焦慮（GD）/transwomen","docId":"性別焦慮（GD）/transwomen","unlisted":false}]}]},"docs":{"性別焦慮（GD）/gd":{"id":"性別焦慮（GD）/gd","title":"什麼是性別焦慮（GD）？","description":"概述","sidebar":"myAutogeneratedSidebar"},"性別焦慮（GD）/transwomen":{"id":"性別焦慮（GD）/transwomen","title":"跨性別女性的性別焦慮","description":"概述","sidebar":"myAutogeneratedSidebar"},"contribute":{"id":"contribute","title":"貢獻者指南","description":"簡介","sidebar":"myAutogeneratedSidebar"},"intro":{"id":"intro","title":"簡介","description":"團隊使命","sidebar":"myAutogeneratedSidebar"}}}}